chaser/__init__.py
chaser/__main__.py
chaser/cli/__init__.py
chaser/cli/access_token_cache.py
chaser/cli/app.py
chaser/cli/choices.py
chaser/cli/constants.py
chaser/cli/deploy.py
chaser/cli/entry_point.py
chaser/cli/info.py
chaser/cli/link.py
chaser/cli/login.py
chaser/cli/logs.py
chaser/cli/new.py
chaser/cli/runtime.py
chaser/cli/secret.py
chaser/cli/start.py
chaser/cli/template.py
chaser_util/__init__.py
chaser_util/archive.py
chaser_util/config.py
chaser_util/env.py
chaser_version/__init__.py
chaser_version/_version_generated.py
test/__init__.py
test/helper.py
test/test_access_token_cache.py
test/test_boilerplate.py
test/test_config.py
test/test_env.py
test/test_runtime.py
connectdev-0.1.0.dist-info/METADATA
connectdev-0.1.0.dist-info/WHEEL
connectdev-0.1.0.dist-info/entry_points.txt
connectdev-0.1.0.dist-info/top_level.txt
connectdev-0.1.0.dist-info/RECORD
