Metadata-Version: 2.1
Name: connectdev
Version: 0.1.0
Summary: Command-line tool for ConnectDev which is a platform that lets you host backends for your AI applications.
Home-page: https://connectdev.io
Author: ConnectDev
Author-email: support@connectdev.io
Classifier: Programming Language :: Python :: 3
Classifier: License :: OSI Approved :: MIT License
Classifier: Operating System :: OS Independent
Requires-Python: >=3.6
Requires-Dist: typer ~=0.9.0
Requires-Dist: rich ~=13.6.0
Requires-Dist: requests ~=2.31.0
Requires-Dist: urllib3 ~=2.0.7
Requires-Dist: pydantic ~=2.4.2
Requires-Dist: progressbar ~=2.5
Requires-Dist: termcolor ~=2.3.0
Requires-Dist: click ~=8.1.7
Requires-Dist: grequests ~=0.7.0
Requires-Dist: gevent ~=23.9.1
Provides-Extra: dev
Requires-Dist: pyinstaller ~=6.3.0 ; extra == 'dev'
Requires-Dist: pytest ~=7.4.2 ; extra == 'dev'
Requires-Dist: pytest-mock ~=3.12.0 ; extra == 'dev'
